datasources/cancergenecensus/diff_versions.py
datasources/cancergenecensus/extract_genes.py
datasources/cancerhotspots/prep_3dhotspots/prep3dhotspots.py
datasources/clinvar/prepare_clinvar.py
datasources/cosmic/prepare_cosmic.py
datasources/exac/expand_exac.py
datasources/moalmanac/create_almanac_db.py
datasources/oncotree/get_oncotree.py
datasources/preclinical/annotated/annotate-copy-numbers.py
datasources/preclinical/annotated/annotate-fusions.py
datasources/preclinical/annotated/annotate-variants.py
moalmanac/__init__.py
moalmanac/annotator.py
moalmanac/config.py
moalmanac/datasources.py
moalmanac/evaluator.py
moalmanac/features.py
moalmanac/illustrator.py
moalmanac/investigator.py
moalmanac/logger.py
moalmanac/matchmaker.py
moalmanac/moalmanac.py
moalmanac/ontologymapper.py
moalmanac/reader.py
moalmanac/reporter.py
moalmanac/run_4x_for_output_regression_test.py
moalmanac/run_example.py
moalmanac/run_output_regression_test.py
moalmanac/simplified_input.py
moalmanac/writer.py
moalmanac/test/__init__.py
moalmanac/test/annotator_tests.py
moalmanac/test/compare_outputs.py
moalmanac/test/datasources_tests.py
moalmanac/test/evaluator_tests.py
moalmanac/test/features_tests.py
moalmanac/test/investigator_tests.py
moalmanac/test/writer_tests.py
moalmanac-0.8.1.dist-info/licenses/LICENSE
moalmanac-0.8.1.dist-info/METADATA
moalmanac-0.8.1.dist-info/WHEEL
moalmanac-0.8.1.dist-info/top_level.txt
moalmanac-0.8.1.dist-info/RECORD
