Metadata-Version: 2.4
Name: moalmanac
Version: 0.8.1
Summary: Short description of your package
Author-email: Brendan Reardon <brendan_reardon@dfci.harvard.edu>
License: GNU-GPL-2.0-only
Requires-Python: >=3.12
License-File: LICENSE
Requires-Dist: flask==3.0.2
Requires-Dist: Frozen-Flask==1.0.2
Requires-Dist: ipykernel==6.29.4
Requires-Dist: jupyter==1.0.0
Requires-Dist: matplotlib==3.8.3
Requires-Dist: numpy==1.26.4
Requires-Dist: pandas==2.2.2
Requires-Dist: requests==2.31.0
Requires-Dist: scikit-learn==1.4.2
Requires-Dist: scipy==1.13.0
Requires-Dist: snfpy==0.2.2
Dynamic: license-file
